{
	"category": "handwriting",
	"dateAdded": "2022-06-10",
	"declaredSubsets": [
		"latin",
		"menu"
	],
	"designer": "Tina Anderson, Corey Anderson",
	"family": "Edu NSW ACT Foundation",
	"id": "edu-nsw-act-foundation",
	"license": {
		"attribution": "Copyright 2022 The AU School Handwriting Fonts Project Authors (https://github.com/MezMerrit/AU-School-Handwriting-Fonts)",
		"id": "OFL-1.1",
		"url": "https://openfontlicense.org/open-font-license-official-text/"
	},
	"origin": {
		"available": true,
		"directory": "ofl/edunswactfoundation",
		"revision": "7380f7cebbf2250460c23fd301b51bcbab162edf",
		"upstream": "googleFonts"
	},
	"project": {
		"repository": "https://github.com/MezMerrit/AU-School-Handwriting-Fonts",
		"revision": "0dbdee65c92d10e24e5d634719054f4f96b69133"
	},
	"sourceFiles": [
		{
			"path": "ofl/edunswactfoundation/EduNSWACTFoundation[wght].ttf",
			"sha256": "5a4b22cc39c04d97472bbe705b9700e864492b853b4941645da60202b796146a",
			"size": 55116,
			"variant": {
				"style": "normal",
				"weight": 400
			}
		}
	],
	"sourceModified": "2026-03-03"
}
