{
	"files": [
		{
			"axes": [],
			"cmap": {
				"codepointCount": 257,
				"sha256": "6385ba1584010c18ec76ed0c7838bec635505ba5d820009aefc7d92cacaa5a0e"
			},
			"colorTables": [],
			"fontVersion": "Version 1.001",
			"outline": "glyf",
			"path": "ofl/skranji/Skranji-Bold.ttf",
			"style": "normal",
			"weight": 700
		},
		{
			"axes": [],
			"cmap": {
				"codepointCount": 257,
				"sha256": "6385ba1584010c18ec76ed0c7838bec635505ba5d820009aefc7d92cacaa5a0e"
			},
			"colorTables": [],
			"fontVersion": "Version 1.001",
			"outline": "glyf",
			"path": "ofl/skranji/Skranji-Regular.ttf",
			"style": "normal",
			"weight": 400
		}
	]
}
