{
	"category": "display",
	"dateAdded": "2012-02-29",
	"declaredSubsets": [
		"latin",
		"latin-ext",
		"menu"
	],
	"designer": "Sideshow",
	"family": "Mystery Quest",
	"id": "mystery-quest",
	"license": {
		"attribution": "Copyright (c) 2012 by Font Diner, Inc DBA Sideshow (diner@fontdiner.com) with Reserved Font Name \"Mystery Quest\"",
		"id": "OFL-1.1",
		"url": "https://openfontlicense.org/open-font-license-official-text/"
	},
	"origin": {
		"available": true,
		"directory": "ofl/mysteryquest",
		"revision": "87a88828090cfdeac3d3db1d061b8884da6be151",
		"upstream": "googleFonts"
	},
	"project": {
		"repository": "https://github.com/googlefonts/googlefontdirectory-hg",
		"revision": "52f780bc9d197280a9f430574e179a5f233c56b6"
	},
	"sourceFiles": [
		{
			"path": "ofl/mysteryquest/MysteryQuest-Regular.ttf",
			"sha256": "fc3fba61be98d7de03964b41175ee5629bcc6958b251f8037ef13eabb5431eb2",
			"size": 42124,
			"variant": {
				"style": "normal",
				"weight": 400
			}
		}
	],
	"sourceModified": "2026-03-25"
}
