{
	"id": "hebrew",
	"ranges": [
		[
			"0",
			"0"
		],
		[
			"D",
			"D"
		],
		[
			"20",
			"20"
		],
		[
			"2D",
			"2D"
		],
		[
			"A0",
			"A0"
		],
		[
			"307",
			"308"
		],
		[
			"591",
			"5C7"
		],
		[
			"5D0",
			"5EA"
		],
		[
			"5EF",
			"5F4"
		],
		[
			"200B",
			"2010"
		],
		[
			"20AA",
			"20AA"
		],
		[
			"25CC",
			"25CC"
		],
		[
			"FB1D",
			"FB36"
		],
		[
			"FB38",
			"FB3C"
		],
		[
			"FB3E",
			"FB3E"
		],
		[
			"FB40",
			"FB41"
		],
		[
			"FB43",
			"FB44"
		],
		[
			"FB46",
			"FB4F"
		]
	],
	"source": {
		"path": "Lib/gfsubsets/data/hebrew_unique-glyphs.nam",
		"revision": "4e66b61575c44f45d065fc5b2cf7c3a85b259472",
		"sha256": "583e4d241bcf362e301533ffb61f6c65ccfeb622b9d59e256a113f2ecf128d81",
		"upstream": "namFiles"
	}
}
