{
	"files": [
		{
			"axes": [
				{
					"default": 100,
					"max": 100,
					"min": 62.5,
					"tag": "wdth"
				},
				{
					"default": 400,
					"max": 900,
					"min": 100,
					"tag": "wght"
				}
			],
			"cmap": {
				"codepointCount": 154,
				"sha256": "244936eaf6e2e233f925e52347d4584486e224ef1c76840d72c3ed31b0559972"
			},
			"colorTables": [],
			"fontVersion": "Version 2.001",
			"outline": "glyf",
			"path": "ofl/notosansgurmukhiui/NotoSansGurmukhiUI[wdth,wght].ttf",
			"style": "normal",
			"weight": {
				"default": 400,
				"max": 900,
				"min": 100
			}
		}
	]
}
