{
	"category": "serif",
	"dateAdded": "2020-11-19",
	"declaredSubsets": [
		"dogra",
		"latin",
		"latin-ext",
		"menu"
	],
	"designer": "Google",
	"family": "Noto Serif Dogra",
	"id": "noto-serif-dogra",
	"license": {
		"attribution": "Copyright 2022 The Noto Project Authors (https://github.com/notofonts/dogra)",
		"id": "OFL-1.1",
		"url": "https://openfontlicense.org/open-font-license-official-text/"
	},
	"origin": {
		"available": true,
		"directory": "ofl/notoserifdogra",
		"revision": "8b0a1d0f5983c89bc2b93f1b5fb55f9e252744b5",
		"upstream": "googleFonts"
	},
	"project": {
		"repository": "https://github.com/notofonts/dogra",
		"revision": "ca3e78b572e9f0a62e7b843905255e7cbd2db380"
	},
	"sourceFiles": [
		{
			"path": "ofl/notoserifdogra/NotoSerifDogra-Regular.ttf",
			"sha256": "82c4680f67a8437f6e237adbc5da559751bb3fcd251e9b82c6d7bd9879896024",
			"size": 94812,
			"variant": {
				"style": "normal",
				"weight": 400
			}
		}
	],
	"sourceModified": "2026-03-12"
}
